{
    "dailyLevel": [
        {
            "date": "2024-06-03",
            "target": 13,
            "numbers": [
                2,
                4,
                6,
                8
            ],
            "solutions": 2,
            "hint": "26 or 28",
            "categorizedSolutions": {
                "(4, 8, 26)": {
                    "('*', '/')": [
                        "26*4/8",
                        "26/8*4",
                        "4*26/8",
                        "4/8*26"
                    ]
                },
                "(4, 6, 28)": {
                    "('+', '/')": [
                        "28/4+6",
                        "6+28/4"
                    ]
                }
            }
        },
        {
            "date": "2024-06-04",
            "target": 5,
            "numbers": [
                6,
                7,
                8,
                9
            ],
            "solutions": 4,
            "hint": "67 or 68 or 96 or /6",
            "categorizedSolutions": {
                "(7, 9, 68)": {
                    "('*', '-')": [
                        "68-7*9",
                        "68-9*7"
                    ]
                },
                "(6, 7, 8, 9)": {
                    "('*', '-', '/')": [
                        "8/6*9-7",
                        "8*9/6-7",
                        "9/6*8-7",
                        "9*8/6-7"
                    ]
                },
                "(8, 9, 67)": {
                    "('*', '-')": [
                        "8*9-67",
                        "9*8-67"
                    ]
                },
                "(7, 8, 96)": {
                    "('-', '/')": [
                        "96/8-7"
                    ]
                }
            }
        },
        {
            "date": "2024-06-05",
            "target": 18,
            "numbers": [
                3,
                4,
                5,
                9
            ],
            "solutions": 3,
            "hint": "45 or 54 or *9",
            "categorizedSolutions": {
                "(3, 9, 54)": {
                    "('*', '/')": [
                        "3*54/9",
                        "3/9*54",
                        "54*3/9",
                        "54/9*3"
                    ]
                },
                "(3, 4, 5, 9)": {
                    "('*', '-', '-')": [
                        "3*9-4-5",
                        "3*9-5-4",
                        "9*3-4-5",
                        "9*3-5-4"
                    ]
                },
                "(3, 9, 45)": {
                    "('*', '-')": [
                        "45-3*9",
                        "45-9*3"
                    ]
                }
            }
        },
        {
            "date": "2024-06-06",
            "target": 30,
            "numbers": [
                2,
                3,
                4,
                5
            ],
            "solutions": 3,
            "hint": "45 or 54 or /2",
            "categorizedSolutions": {
                "(2, 3, 45)": {
                    "('*', '/')": [
                        "2/3*45",
                        "2*45/3",
                        "45*2/3",
                        "45/3*2"
                    ]
                },
                "(2, 3, 4, 5)": {
                    "('*', '*', '/')": [
                        "3/2*4*5",
                        "3/2*5*4",
                        "3*4/2*5",
                        "3*4*5/2",
                        "3*5/2*4",
                        "3*5*4/2",
                        "4/2*3*5",
                        "4/2*5*3",
                        "4*3/2*5",
                        "4*3*5/2",
                        "4*5/2*3",
                        "4*5*3/2",
                        "5/2*3*4",
                        "5/2*4*3",
                        "5*3/2*4",
                        "5*3*4/2",
                        "5*4/2*3",
                        "5*4*3/2"
                    ]
                },
                "(2, 3, 54)": {
                    "('+', '/')": [
                        "3+54/2",
                        "54/2+3"
                    ]
                }
            }
        },
        {
            "date": "2024-06-07",
            "target": 12,
            "numbers": [
                2,
                4,
                5,
                6
            ],
            "solutions": 7,
            "hint": "64 or 56 or 42(2) or /2 or *4 or *2",
            "categorizedSolutions": {
                "(2, 4, 5, 6)": {
                    "('*', '+', '-')": [
                        "2*5-4+6",
                        "2*5+6-4",
                        "5*2-4+6",
                        "5*2+6-4",
                        "6+2*5-4",
                        "6-4+2*5",
                        "6-4+5*2",
                        "6+5*2-4"
                    ],
                    "('*', '-', '-')": [
                        "4*5-2-6",
                        "4*5-6-2",
                        "5*4-2-6",
                        "5*4-6-2"
                    ],
                    "('+', '+', '/')": [
                        "4+5+6/2",
                        "4+6/2+5",
                        "5+4+6/2",
                        "5+6/2+4",
                        "6/2+4+5",
                        "6/2+5+4"
                    ]
                },
                "(5, 6, 42)": {
                    "('*', '-')": [
                        "42-5*6",
                        "42-6*5"
                    ],
                    "('+', '/')": [
                        "42/6+5",
                        "5+42/6"
                    ]
                },
                "(2, 4, 56)": {
                    "('-', '/')": [
                        "56/4-2"
                    ]
                },
                "(52, 64)": {
                    "('-',)": [
                        "64-52"
                    ]
                }
            }
        },
        {
            "date": "2024-06-08",
            "target": 2,
            "numbers": [
                4,
                5,
                7,
                9
            ],
            "solutions": 3,
            "hint": "45 or 47 or 49",
            "categorizedSolutions": {
                "(5, 9, 47)": {
                    "('*', '-')": [
                        "47-5*9",
                        "47-9*5"
                    ]
                },
                "(5, 7, 49)": {
                    "('-', '/')": [
                        "49/7-5"
                    ]
                },
                "(7, 9, 45)": {
                    "('-', '/')": [
                        "7-45/9"
                    ]
                }
            }
        },
        {
            "date": "2024-06-09",
            "target": 14,
            "numbers": [
                2,
                5,
                6,
                8
            ],
            "solutions": 4,
            "hint": "26 or 56 or *2 or /2",
            "categorizedSolutions": {
                "(2, 8, 56)": {
                    "('*', '/')": [
                        "2*56/8",
                        "2/8*56",
                        "56*2/8",
                        "56/8*2"
                    ]
                },
                "(2, 5, 6, 8)": {
                    "('*', '-', '/')": [
                        "5/2*8-6",
                        "5*8/2-6",
                        "8/2*5-6",
                        "8*5/2-6"
                    ],
                    "('*', '*', '-')": [
                        "5*6-2*8",
                        "5*6-8*2",
                        "6*5-2*8",
                        "6*5-8*2"
                    ]
                },
                "(5, 8, 26)": {
                    "('*', '-')": [
                        "5*8-26",
                        "8*5-26"
                    ]
                }
            }
        },
        {
            "date": "2024-06-10",
            "target": 18,
            "numbers": [
                3,
                5,
                6,
                9
            ],
            "solutions": 4,
            "hint": "63 or 69 or *5(2)",
            "categorizedSolutions": {
                "(3, 5, 6, 9)": {
                    "('*', '+', '-')": [
                        "3*5-6+9",
                        "3*5+9-6",
                        "5*3-6+9",
                        "5*3+9-6",
                        "9+3*5-6",
                        "9+5*3-6",
                        "9-6+3*5",
                        "9-6+5*3"
                    ],
                    "('*', '-', '-')": [
                        "5*6-3-9",
                        "5*6-9-3",
                        "6*5-3-9",
                        "6*5-9-3"
                    ]
                },
                "(5, 9, 63)": {
                    "('*', '-')": [
                        "63-5*9",
                        "63-9*5"
                    ]
                },
                "(3, 5, 69)": {
                    "('-', '/')": [
                        "69/3-5"
                    ]
                }
            }
        },
        {
            "date": "2024-06-11",
            "target": 7,
            "numbers": [
                1,
                2,
                4,
                7
            ],
            "solutions": 4,
            "hint": "21(2) or 24 or 42",
            "categorizedSolutions": {
                "(1, 7, 42)": {
                    "('+', '/')": [
                        "1+42/7",
                        "42/7+1"
                    ]
                },
                "(4, 7, 21)": {
                    "('+', '/')": [
                        "21/7+4",
                        "4+21/7"
                    ],
                    "('*', '-')": [
                        "4*7-21",
                        "7*4-21"
                    ]
                },
                "(17, 24)": {
                    "('-',)": [
                        "24-17"
                    ]
                }
            }
        },
        {
            "date": "2024-06-12",
            "target": 3,
            "numbers": [
                4,
                5,
                6,
                8
            ],
            "solutions": 6,
            "hint": "45 or 64 or 48 or 56 or /4 or -4",
            "categorizedSolutions": {
                "(5, 6, 48)": {
                    "('-', '/')": [
                        "48/6-5"
                    ]
                },
                "(4, 5, 6, 8)": {
                    "('+', '-', '-')": [
                        "5-4-6+8",
                        "5-4+8-6",
                        "5-6-4+8",
                        "5-6+8-4",
                        "5+8-4-6",
                        "5+8-6-4",
                        "8-4+5-6",
                        "8-4-6+5",
                        "8+5-4-6",
                        "8+5-6-4",
                        "8-6-4+5",
                        "8-6+5-4"
                    ],
                    "('+', '-', '/')": [
                        "6-5+8/4",
                        "6+8/4-5",
                        "8/4-5+6",
                        "8/4+6-5"
                    ]
                },
                "(4, 8, 56)": {
                    "('-', '/')": [
                        "56/8-4"
                    ]
                },
                "(5, 8, 64)": {
                    "('-', '/')": [
                        "64/8-5"
                    ]
                },
                "(6, 8, 45)": {
                    "('*', '-')": [
                        "6*8-45",
                        "8*6-45"
                    ]
                }
            }
        },
        {
            "date": "2024-06-13",
            "target": 23,
            "numbers": [
                5,
                7,
                8,
                9
            ],
            "solutions": 2,
            "hint": "98 or *9",
            "categorizedSolutions": {
                "(5, 7, 8, 9)": {
                    "('*', '*', '-')": [
                        "7*9-5*8",
                        "7*9-8*5",
                        "9*7-5*8",
                        "9*7-8*5"
                    ]
                },
                "(75, 98)": {
                    "('-',)": [
                        "98-75"
                    ]
                }
            }
        },
        {
            "date": "2024-06-14",
            "target": 20,
            "numbers": [
                3,
                6,
                7,
                8
            ],
            "solutions": 2,
            "hint": "78 or 36",
            "categorizedSolutions": {
                "(3, 6, 78)": {
                    "('-', '/')": [
                        "78/3-6"
                    ]
                },
                "(7, 8, 36)": {
                    "('*', '-')": [
                        "7*8-36",
                        "8*7-36"
                    ]
                }
            }
        },
        {
            "date": "2024-06-15",
            "target": 14,
            "numbers": [
                1,
                5,
                7,
                8
            ],
            "solutions": 3,
            "hint": "17 or 15 or 85",
            "categorizedSolutions": {
                "(7, 8, 15)": {
                    "('+', '-')": [
                        "15+7-8",
                        "15-8+7",
                        "7+15-8",
                        "7-8+15"
                    ]
                },
                "(5, 8, 17)": {
                    "('+', '-')": [
                        "17+5-8",
                        "17-8+5",
                        "5+17-8",
                        "5-8+17"
                    ]
                },
                "(71, 85)": {
                    "('-',)": [
                        "85-71"
                    ]
                }
            }
        },
        {
            "date": "2024-06-16",
            "target": 45,
            "numbers": [
                1,
                3,
                5,
                9
            ],
            "solutions": 6,
            "hint": "39 or 35 or 53 or 15 or 51 or 31",
            "categorizedSolutions": {
                "(1, 9, 35)": {
                    "('+', '+')": [
                        "1+35+9",
                        "1+9+35",
                        "35+1+9",
                        "35+9+1",
                        "9+1+35",
                        "9+35+1"
                    ]
                },
                "(1, 5, 39)": {
                    "('+', '+')": [
                        "1+39+5",
                        "1+5+39",
                        "39+1+5",
                        "39+5+1",
                        "5+1+39",
                        "5+39+1"
                    ]
                },
                "(3, 9, 15)": {
                    "('*', '/')": [
                        "15/3*9",
                        "15*9/3",
                        "9*15/3",
                        "9/3*15"
                    ]
                },
                "(1, 9, 53)": {
                    "('+', '-')": [
                        "1+53-9",
                        "1-9+53",
                        "53+1-9",
                        "53-9+1"
                    ]
                },
                "(5, 9, 31)": {
                    "('+', '+')": [
                        "31+5+9",
                        "31+9+5",
                        "5+31+9",
                        "5+9+31",
                        "9+31+5",
                        "9+5+31"
                    ]
                },
                "(3, 9, 51)": {
                    "('+', '-')": [
                        "3+51-9",
                        "3-9+51",
                        "51+3-9",
                        "51-9+3"
                    ]
                }
            }
        },
        {
            "date": "2024-06-17",
            "target": 17,
            "numbers": [
                4,
                5,
                6,
                8
            ],
            "solutions": 3,
            "hint": "48 or 54 or /4",
            "categorizedSolutions": {
                "(6, 8, 54)": {
                    "('+', '/')": [
                        "54/6+8",
                        "8+54/6"
                    ]
                },
                "(4, 5, 6, 8)": {
                    "('*', '+', '/')": [
                        "5+6/4*8",
                        "5+6*8/4",
                        "5+8/4*6",
                        "5+8*6/4",
                        "6/4*8+5",
                        "6*8/4+5",
                        "8/4*6+5",
                        "8*6/4+5"
                    ]
                },
                "(48, 65)": {
                    "('-',)": [
                        "65-48"
                    ]
                }
            }
        },
        {
            "date": "2024-06-18",
            "target": 11,
            "numbers": [
                4,
                5,
                6,
                7
            ],
            "solutions": 4,
            "hint": "46 or 57 or 64 or *6",
            "categorizedSolutions": {
                "(5, 7, 46)": {
                    "('*', '-')": [
                        "46-5*7",
                        "46-7*5"
                    ]
                },
                "(46, 57)": {
                    "('-',)": [
                        "57-46"
                    ]
                },
                "(4, 5, 6, 7)": {
                    "('*', '*', '-')": [
                        "5*7-4*6",
                        "5*7-6*4",
                        "7*5-4*6",
                        "7*5-6*4"
                    ]
                },
                "(64, 75)": {
                    "('-',)": [
                        "75-64"
                    ]
                }
            }
        },
        {
            "date": "2024-06-19",
            "target": 0,
            "numbers": [
                2,
                3,
                4,
                8
            ],
            "solutions": 4,
            "hint": "24 or 32",
            "categorizedSolutions": {
                "(3, 8, 24)": {
                    "('*', '-')": [
                        "24-3*8",
                        "24-8*3",
                        "3*8-24",
                        "8*3-24"
                    ],
                    "('-', '/')": [
                        "24/3-8",
                        "24/8-3",
                        "3-24/8",
                        "8-24/3"
                    ]
                },
                "(4, 8, 32)": {
                    "('*', '-')": [
                        "32-4*8",
                        "32-8*4",
                        "4*8-32",
                        "8*4-32"
                    ],
                    "('-', '/')": [
                        "32/4-8",
                        "32/8-4",
                        "4-32/8",
                        "8-32/4"
                    ]
                }
            }
        },
        {
            "date": "2024-06-20",
            "target": 16,
            "numbers": [
                1,
                7,
                8,
                9
            ],
            "solutions": 4,
            "hint": "18 or 17 or 81 or 97",
            "categorizedSolutions": {
                "(8, 9, 17)": {
                    "('+', '-')": [
                        "17+8-9",
                        "17-9+8",
                        "8+17-9",
                        "8-9+17"
                    ]
                },
                "(7, 9, 18)": {
                    "('+', '-')": [
                        "18+7-9",
                        "18-9+7",
                        "7+18-9",
                        "7-9+18"
                    ]
                },
                "(7, 9, 81)": {
                    "('+', '/')": [
                        "7+81/9",
                        "81/9+7"
                    ]
                },
                "(81, 97)": {
                    "('-',)": [
                        "97-81"
                    ]
                }
            }
        },
        {
            "date": "2024-06-21",
            "target": 21,
            "numbers": [
                1,
                2,
                3,
                5
            ],
            "solutions": 5,
            "hint": "25 or 15 or 13 or 31 or 52",
            "categorizedSolutions": {
                "(2, 5, 13)": {
                    "('*', '-')": [
                        "13*2-5",
                        "2*13-5"
                    ]
                },
                "(2, 3, 15)": {
                    "('*', '+')": [
                        "15+2*3",
                        "15+3*2",
                        "2*3+15",
                        "3*2+15"
                    ]
                },
                "(1, 3, 25)": {
                    "('-', '-')": [
                        "25-1-3",
                        "25-3-1"
                    ]
                },
                "(2, 5, 31)": {
                    "('*', '-')": [
                        "31-2*5",
                        "31-5*2"
                    ]
                },
                "(31, 52)": {
                    "('-',)": [
                        "52-31"
                    ]
                }
            }
        },
        {
            "date": "2024-06-22",
            "target": 9,
            "numbers": [
                5,
                6,
                7,
                8
            ],
            "solutions": 4,
            "hint": "57 or 65 or 58 or 76",
            "categorizedSolutions": {
                "(6, 8, 57)": {
                    "('*', '-')": [
                        "57-6*8",
                        "57-8*6"
                    ]
                },
                "(7, 8, 65)": {
                    "('*', '-')": [
                        "65-7*8",
                        "65-8*7"
                    ]
                },
                "(58, 67)": {
                    "('-',)": [
                        "67-58"
                    ]
                },
                "(76, 85)": {
                    "('-',)": [
                        "85-76"
                    ]
                }
            }
        },
        {
            "date": "2024-06-23",
            "target": 23,
            "numbers": [
                2,
                5,
                6,
                8
            ],
            "solutions": 6,
            "hint": "58 or 26 or 25(2) or 85, /2",
            "categorizedSolutions": {
                "(6, 8, 25)": {
                    "('+', '-')": [
                        "25+6-8",
                        "25-8+6",
                        "6+25-8",
                        "6-8+25"
                    ],
                    "('*', '-')": [
                        "6*8-25",
                        "8*6-25"
                    ]
                },
                "(5, 8, 26)": {
                    "('+', '-')": [
                        "26+5-8",
                        "26-8+5",
                        "5+26-8",
                        "5-8+26"
                    ]
                },
                "(2, 5, 6, 8)": {
                    "('*', '+', '/')": [
                        "5/2*6+8",
                        "5*6/2+8",
                        "6/2*5+8",
                        "6*5/2+8",
                        "8+5/2*6",
                        "8+5*6/2",
                        "8+6/2*5",
                        "8+6*5/2"
                    ]
                },
                "(2, 6, 58)": {
                    "('-', '/')": [
                        "58/2-6"
                    ]
                },
                "(62, 85)": {
                    "('-',)": [
                        "85-62"
                    ]
                }
            }
        },
        {
            "date": "2024-06-24",
            "target": 36,
            "numbers": [
                2,
                3,
                4,
                9
            ],
            "solutions": 6,
            "hint": "43 or 29 or 24 or 42 or 23 or /9",
            "categorizedSolutions": {
                "(4, 9, 23)": {
                    "('+', '+')": [
                        "23+4+9",
                        "23+9+4",
                        "4+23+9",
                        "4+9+23",
                        "9+23+4",
                        "9+4+23"
                    ]
                },
                "(3, 9, 24)": {
                    "('+', '+')": [
                        "24+3+9",
                        "24+9+3",
                        "3+24+9",
                        "3+9+24",
                        "9+24+3",
                        "9+3+24"
                    ]
                },
                "(2, 9, 43)": {
                    "('+', '-')": [
                        "2+43-9",
                        "2-9+43",
                        "43+2-9",
                        "43-9+2"
                    ]
                },
                "(3, 4, 29)": {
                    "('+', '+')": [
                        "29+3+4",
                        "29+4+3",
                        "3+29+4",
                        "3+4+29",
                        "4+29+3",
                        "4+3+29"
                    ]
                },
                "(9, 324)": {
                    "('/',)": [
                        "324/9"
                    ]
                },
                "(3, 9, 42)": {
                    "('+', '-')": [
                        "3+42-9",
                        "3-9+42",
                        "42+3-9",
                        "42-9+3"
                    ]
                }
            }
        },
        {
            "date": "2024-06-25",
            "target": 25,
            "numbers": [
                2,
                4,
                6,
                7
            ],
            "solutions": 6,
            "hint": "/2(2) or 64 or 27 or 24 or 67",
            "categorizedSolutions": {
                "(6, 7, 24)": {
                    "('+', '-')": [
                        "24-6+7",
                        "24+7-6",
                        "7+24-6",
                        "7-6+24"
                    ]
                },
                "(4, 6, 27)": {
                    "('+', '-')": [
                        "27+4-6",
                        "27-6+4",
                        "4+27-6",
                        "4-6+27"
                    ]
                },
                "(2, 4, 6, 7)": {
                    "('*', '+', '/')": [
                        "4+6/2*7",
                        "4+6*7/2",
                        "4+7/2*6",
                        "4+7*6/2",
                        "6/2*7+4",
                        "6*7/2+4",
                        "7/2*6+4",
                        "7*6/2+4"
                    ],
                    "('*', '-', '/')": [
                        "4*7-6/2",
                        "7*4-6/2"
                    ]
                },
                "(2, 7, 64)": {
                    "('-', '/')": [
                        "64/2-7"
                    ]
                },
                "(42, 67)": {
                    "('-',)": [
                        "67-42"
                    ]
                }
            }
        },
        {
            "date": "2024-06-26",
            "target": 22,
            "numbers": [
                2,
                3,
                8,
                9
            ],
            "solutions": 5,
            "hint": "+9 or -2 or +9 or 28 or 23",
            "categorizedSolutions": {
                "(8, 9, 23)": {
                    "('+', '-')": [
                        "23+8-9",
                        "23-9+8",
                        "8+23-9",
                        "8-9+23"
                    ]
                },
                "(2, 3, 8, 9)": {
                    "('+', '+', '+')": [
                        "2+3+8+9",
                        "2+3+9+8",
                        "2+8+3+9",
                        "2+8+9+3",
                        "2+9+3+8",
                        "2+9+8+3",
                        "3+2+8+9",
                        "3+2+9+8",
                        "3+8+2+9",
                        "3+8+9+2",
                        "3+9+2+8",
                        "3+9+8+2",
                        "8+2+3+9",
                        "8+2+9+3",
                        "8+3+2+9",
                        "8+3+9+2",
                        "8+9+2+3",
                        "8+9+3+2",
                        "9+2+3+8",
                        "9+2+8+3",
                        "9+3+2+8",
                        "9+3+8+2",
                        "9+8+2+3",
                        "9+8+3+2"
                    ],
                    "('*', '+', '-')": [
                        "2*8-3+9",
                        "2*8+9-3",
                        "8*2-3+9",
                        "8*2+9-3",
                        "9+2*8-3",
                        "9-3+2*8",
                        "9-3+8*2",
                        "9+8*2-3"
                    ],
                    "('*', '-', '/')": [
                        "8/3*9-2",
                        "8*9/3-2",
                        "9/3*8-2",
                        "9*8/3-2"
                    ]
                },
                "(3, 9, 28)": {
                    "('+', '-')": [
                        "28+3-9",
                        "28-9+3",
                        "3+28-9",
                        "3-9+28"
                    ]
                }
            }
        },
        {
            "date": "2024-06-27",
            "target": 3,
            "numbers": [
                2,
                6,
                7,
                8
            ],
            "solutions": 6,
            "hint": "*6 or -7 or -2 or +6 or 72 or 78",
            "categorizedSolutions": {
                "(2, 6, 7, 8)": {
                    "('*', '-', '-')": [
                        "2*8-6-7",
                        "2*8-7-6",
                        "8*2-6-7",
                        "8*2-7-6"
                    ],
                    "('+', '-', '-')": [
                        "6-2+7-8",
                        "6-2-8+7",
                        "6+7-2-8",
                        "6+7-8-2",
                        "6-8-2+7",
                        "6-8+7-2",
                        "7-2+6-8",
                        "7-2-8+6",
                        "7+6-2-8",
                        "7+6-8-2",
                        "7-8-2+6",
                        "7-8+6-2"
                    ],
                    "('+', '-', '/')": [
                        "6-7+8/2",
                        "6+8/2-7",
                        "8/2+6-7",
                        "8/2-7+6"
                    ],
                    "('*', '+', '-')": [
                        "7-2*6+8",
                        "7-6*2+8",
                        "7+8-2*6",
                        "7+8-6*2",
                        "8-2*6+7",
                        "8-6*2+7",
                        "8+7-2*6",
                        "8+7-6*2"
                    ]
                },
                "(6, 8, 72)": {
                    "('-', '/')": [
                        "72/8-6"
                    ]
                },
                "(26, 78)": {
                    "('/',)": [
                        "78/26"
                    ]
                }
            }
        },
        {
            "date": "2024-06-28",
            "target": 1,
            "numbers": [
                2,
                3,
                4,
                6
            ],
            "solutions": 8,
            "hint": "*2 or *4 or +6 or /4 or /2 or /6 or 24 or 23",
            "categorizedSolutions": {
                "(2, 3, 4, 6)": {
                    "('+', '-', '-')": [
                        "2-3-4+6",
                        "2-3+6-4",
                        "2-4-3+6",
                        "2-4+6-3",
                        "2+6-3-4",
                        "2+6-4-3",
                        "6+2-3-4",
                        "6+2-4-3",
                        "6-3+2-4",
                        "6-3-4+2",
                        "6-4+2-3",
                        "6-4-3+2"
                    ],
                    "('*', '/', '/')": [
                        "2/3/4*6",
                        "2/3*6/4",
                        "2/4/3*6",
                        "2/4*6/3",
                        "2*6/3/4",
                        "2*6/4/3",
                        "3/2*4/6",
                        "3/2/6*4",
                        "3*4/2/6",
                        "3*4/6/2",
                        "3/6/2*4",
                        "3/6*4/2",
                        "4/2*3/6",
                        "4/2/6*3",
                        "4*3/2/6",
                        "4*3/6/2",
                        "4/6/2*3",
                        "4/6*3/2",
                        "6*2/3/4",
                        "6*2/4/3",
                        "6/3*2/4",
                        "6/3/4*2",
                        "6/4*2/3",
                        "6/4/3*2"
                    ],
                    "('+', '/', '/')": [
                        "2/4+3/6",
                        "3/6+2/4"
                    ],
                    "('*', '+', '-')": [
                        "3-2*4+6",
                        "3-4*2+6",
                        "3+6-2*4",
                        "3+6-4*2",
                        "6-2*4+3",
                        "6+3-2*4",
                        "6+3-4*2",
                        "6-4*2+3"
                    ],
                    "('-', '/', '/')": [
                        "4/3-2/6"
                    ],
                    "('-', '-', '/')": [
                        "6-3-4/2",
                        "6-4/2-3"
                    ]
                },
                "(3, 6, 24)": {
                    "('-', '/')": [
                        "24/6-3"
                    ]
                },
                "(4, 6, 23)": {
                    "('*', '-')": [
                        "4*6-23",
                        "6*4-23"
                    ]
                }
            }
        },
        {
            "date": "2024-06-29",
            "target": 29,
            "numbers": [
                2,
                3,
                6,
                9
            ],
            "solutions": 5,
            "hint": "*3 or 36 or 26 or 32 or 92",
            "categorizedSolutions": {
                "(2, 9, 36)": {
                    "('+', '-')": [
                        "2+36-9",
                        "2-9+36",
                        "36+2-9",
                        "36-9+2"
                    ]
                },
                "(2, 3, 6, 9)": {
                    "('*', '+', '+')": [
                        "2+3*6+9",
                        "2+6*3+9",
                        "2+9+3*6",
                        "2+9+6*3",
                        "3*6+2+9",
                        "3*6+9+2",
                        "6*3+2+9",
                        "6*3+9+2",
                        "9+2+3*6",
                        "9+2+6*3",
                        "9+3*6+2",
                        "9+6*3+2"
                    ]
                },
                "(3, 9, 26)": {
                    "('+', '/')": [
                        "26+9/3",
                        "9/3+26"
                    ]
                },
                "(6, 9, 32)": {
                    "('+', '-')": [
                        "32+6-9",
                        "32-9+6",
                        "6+32-9",
                        "6-9+32"
                    ]
                },
                "(63, 92)": {
                    "('-',)": [
                        "92-63"
                    ]
                }
            }
        },
        {
            "date": "2024-06-30",
            "target": 23,
            "numbers": [
                3,
                6,
                7,
                8
            ],
            "solutions": 4,
            "hint": "+8 or +7 or 87 or 37",
            "categorizedSolutions": {
                "(6, 8, 37)": {
                    "('-', '-')": [
                        "37-6-8",
                        "37-8-6"
                    ]
                },
                "(3, 6, 7, 8)": {
                    "('*', '+', '-')": [
                        "3*7-6+8",
                        "3*7+8-6",
                        "3*8+6-7",
                        "3*8-7+6",
                        "6+3*8-7",
                        "6-7+3*8",
                        "6-7+8*3",
                        "6+8*3-7",
                        "7*3-6+8",
                        "7*3+8-6",
                        "8*3+6-7",
                        "8+3*7-6",
                        "8*3-7+6",
                        "8-6+3*7",
                        "8-6+7*3",
                        "8+7*3-6"
                    ],
                    "('*', '+', '/')": [
                        "6/3*8+7",
                        "6*8/3+7",
                        "7+6/3*8",
                        "7+6*8/3",
                        "7+8/3*6",
                        "7+8*6/3",
                        "8/3*6+7",
                        "8*6/3+7"
                    ]
                },
                "(3, 6, 87)": {
                    "('-', '/')": [
                        "87/3-6"
                    ]
                }
            }
        },
        {
            "date": "2024-07-01",
            "target": 15,
            "numbers": [
                2,
                3,
                4,
                7
            ],
            "solutions": 7,
            "hint": "-3 or -4 or 27 or 72 or 24 or 32 or 47",
            "categorizedSolutions": {
                "(3, 7, 24)": {
                    "('+', '/')": [
                        "24/3+7",
                        "7+24/3"
                    ]
                },
                "(3, 4, 27)": {
                    "('*', '-')": [
                        "27-3*4",
                        "27-4*3"
                    ]
                },
                "(2, 3, 4, 7)": {
                    "('*', '+', '-')": [
                        "2*7-3+4",
                        "2*7+4-3",
                        "4+2*7-3",
                        "4-3+2*7",
                        "4-3+7*2",
                        "4+7*2-3",
                        "7*2-3+4",
                        "7*2+4-3"
                    ],
                    "('*', '-', '-')": [
                        "3*7-2-4",
                        "3*7-4-2",
                        "7*3-2-4",
                        "7*3-4-2"
                    ]
                },
                "(4, 7, 32)": {
                    "('+', '/')": [
                        "32/4+7",
                        "7+32/4"
                    ]
                },
                "(32, 47)": {
                    "('-',)": [
                        "47-32"
                    ]
                },
                "(3, 4, 72)": {
                    "('-', '/')": [
                        "72/4-3"
                    ]
                }
            }
        },
        {
            "date": "2024-07-02",
            "target": 7,
            "numbers": [
                3,
                5,
                8,
                9
            ],
            "solutions": 3,
            "hint": "-8 or +5 or 38",
            "categorizedSolutions": {
                "(3, 5, 8, 9)": {
                    "('+', '+', '-')": [
                        "3+5+8-9",
                        "3+5-9+8",
                        "3+8+5-9",
                        "3+8-9+5",
                        "3-9+5+8",
                        "3-9+8+5",
                        "5+3+8-9",
                        "5+3-9+8",
                        "5+8+3-9",
                        "5+8-9+3",
                        "5-9+3+8",
                        "5-9+8+3",
                        "8+3+5-9",
                        "8+3-9+5",
                        "8+5+3-9",
                        "8+5-9+3",
                        "8-9+3+5",
                        "8-9+5+3"
                    ],
                    "('*', '-', '/')": [
                        "5/3*9-8",
                        "5*9/3-8",
                        "9/3*5-8",
                        "9*5/3-8"
                    ]
                },
                "(5, 9, 38)": {
                    "('*', '-')": [
                        "5*9-38",
                        "9*5-38"
                    ]
                }
            }
        },
        {
            "date": "2024-07-03",
            "target": 15,
            "numbers": [
                3,
                6,
                8,
                9
            ],
            "solutions": 5,
            "hint": "*9 or +9 or 69 or 96 or 63",
            "categorizedSolutions": {
                "(3, 6, 8, 9)": {
                    "('*', '+', '/')": [
                        "3+8/6*9",
                        "3+8*9/6",
                        "3+9/6*8",
                        "3+9*8/6",
                        "8/6*9+3",
                        "8*9/6+3",
                        "9/6*8+3",
                        "9*8/6+3"
                    ],
                    "('+', '-', '/')": [
                        "8-6/3+9",
                        "8+9-6/3",
                        "9-6/3+8",
                        "9+8-6/3"
                    ]
                },
                "(3, 8, 96)": {
                    "('+', '/')": [
                        "3+96/8",
                        "96/8+3"
                    ]
                },
                "(8, 9, 63)": {
                    "('+', '/')": [
                        "63/9+8",
                        "8+63/9"
                    ]
                },
                "(3, 8, 69)": {
                    "('-', '/')": [
                        "69/3-8"
                    ]
                }
            }
        },
        {
            "date": "2024-07-04",
            "target": 8,
            "numbers": [
                2,
                3,
                4,
                6
            ],
            "solutions": 6,
            "hint": "+2 or /3 or +2 or 42 or 32 or 34",
            "categorizedSolutions": {
                "(2, 3, 4, 6)": {
                    "('*', '+', '-')": [
                        "2+3*4-6",
                        "2*3-4+6",
                        "2*3+6-4",
                        "2+4*3-6",
                        "2-6+3*4",
                        "2-6+4*3",
                        "3*2-4+6",
                        "3*2+6-4",
                        "3*4+2-6",
                        "3*4-6+2",
                        "4*3+2-6",
                        "4*3-6+2",
                        "6+2*3-4",
                        "6+3*2-4",
                        "6-4+2*3",
                        "6-4+3*2"
                    ],
                    "('*', '+', '/')": [
                        "2/3*6+4",
                        "2*6/3+4",
                        "4+2/3*6",
                        "4+2*6/3",
                        "4+6*2/3",
                        "4+6/3*2",
                        "6*2/3+4",
                        "6/3*2+4"
                    ],
                    "('+', '+', '/')": [
                        "2+4+6/3",
                        "2+6/3+4",
                        "4+2+6/3",
                        "4+6/3+2",
                        "6/3+2+4",
                        "6/3+4+2"
                    ]
                },
                "(4, 6, 32)": {
                    "('*', '-')": [
                        "32-4*6",
                        "32-6*4"
                    ]
                },
                "(26, 34)": {
                    "('-',)": [
                        "34-26"
                    ]
                },
                "(3, 6, 42)": {
                    "('-', '/')": [
                        "42/3-6"
                    ]
                }
            }
        },
        {
            "date": "2024-07-05",
            "target": 1,
            "numbers": [
                2,
                4,
                6,
                7
            ],
            "solutions": 5,
            "hint": "-4 or -2 or -7 or 42 or 42",
            "categorizedSolutions": {
                "(2, 4, 6, 7)": {
                    "('*', '-', '-')": [
                        "2*6-4-7",
                        "2*6-7-4",
                        "6*2-4-7",
                        "6*2-7-4"
                    ],
                    "('+', '-', '-')": [
                        "4-2+6-7",
                        "4-2-7+6",
                        "4+6-2-7",
                        "4+6-7-2",
                        "4-7-2+6",
                        "4-7+6-2",
                        "6-2+4-7",
                        "6-2-7+4",
                        "6+4-2-7",
                        "6+4-7-2",
                        "6-7-2+4",
                        "6-7+4-2"
                    ],
                    "('+', '-', '/')": [
                        "4/2+6-7",
                        "4/2-7+6",
                        "6+4/2-7",
                        "6-7+4/2"
                    ]
                },
                "(6, 7, 42)": {
                    "('/', '/')": [
                        "42/6/7",
                        "42/7/6"
                    ],
                    "('*', '/')": [
                        "6/42*7",
                        "6*7/42",
                        "7/42*6",
                        "7*6/42"
                    ]
                }
            }
        },
        {
            "date": "2024-07-06",
            "target": 29,
            "numbers": [
                2,
                6,
                7,
                8
            ],
            "solutions": 5,
            "hint": "+6 or +8 or 87 or 28 or 27",
            "categorizedSolutions": {
                "(2, 6, 87)": {
                    "('*', '/')": [
                        "2/6*87",
                        "2*87/6",
                        "87*2/6",
                        "87/6*2"
                    ]
                },
                "(6, 8, 27)": {
                    "('+', '-')": [
                        "27-6+8",
                        "27+8-6",
                        "8+27-6",
                        "8-6+27"
                    ]
                },
                "(6, 7, 28)": {
                    "('+', '-')": [
                        "28-6+7",
                        "28+7-6",
                        "7+28-6",
                        "7-6+28"
                    ]
                },
                "(2, 6, 7, 8)": {
                    "('*', '+', '+')": [
                        "2*8+6+7",
                        "2*8+7+6",
                        "6+2*8+7",
                        "6+7+2*8",
                        "6+7+8*2",
                        "6+8*2+7",
                        "7+2*8+6",
                        "7+6+2*8",
                        "7+6+8*2",
                        "7+8*2+6",
                        "8*2+6+7",
                        "8*2+7+6"
                    ],
                    "('*', '+', '/')": [
                        "6/2*7+8",
                        "6*7/2+8",
                        "7/2*6+8",
                        "7*6/2+8",
                        "8+6/2*7",
                        "8+6*7/2",
                        "8+7/2*6",
                        "8+7*6/2"
                    ]
                }
            }
        },
        {
            "date": "2024-07-07",
            "target": 8,
            "numbers": [
                2,
                3,
                6,
                8
            ],
            "solutions": 6,
            "hint": "*3 or *2 or -8 or *8 or /3 or 36",
            "categorizedSolutions": {
                "(2, 3, 6, 8)": {
                    "('*', '+', '-')": [
                        "2*3-6+8",
                        "2*3+8-6",
                        "3*2-6+8",
                        "3*2+8-6",
                        "6-2*3+8",
                        "6-3*2+8",
                        "6+8-2*3",
                        "6+8-3*2",
                        "8+2*3-6",
                        "8-2*3+6",
                        "8+3*2-6",
                        "8-3*2+6",
                        "8+6-2*3",
                        "8-6+2*3",
                        "8+6-3*2",
                        "8-6+3*2"
                    ],
                    "('*', '*', '/')": [
                        "2*3/6*8",
                        "2*3*8/6",
                        "2/6*3*8",
                        "2/6*8*3",
                        "2*8*3/6",
                        "2*8/6*3",
                        "3*2/6*8",
                        "3*2*8/6",
                        "3/6*2*8",
                        "3/6*8*2",
                        "3*8*2/6",
                        "3*8/6*2",
                        "8*2*3/6",
                        "8*2/6*3",
                        "8*3*2/6",
                        "8*3/6*2",
                        "8/6*2*3",
                        "8/6*3*2"
                    ],
                    "('+', '-', '/')": [
                        "2-6/3+8",
                        "2+8-6/3",
                        "3-6/2+8",
                        "3+8-6/2",
                        "6/2-3+8",
                        "6/2+8-3",
                        "6/3-2+8",
                        "6/3+8-2",
                        "8+2-6/3",
                        "8-2+6/3",
                        "8+3-6/2",
                        "8-3+6/2",
                        "8+6/2-3",
                        "8-6/2+3",
                        "8+6/3-2",
                        "8-6/3+2"
                    ],
                    "('*', '-', '-')": [
                        "3*6-2-8",
                        "3*6-8-2",
                        "6*3-2-8",
                        "6*3-8-2"
                    ],
                    "('*', '/', '/')": [
                        "6/2/3*8",
                        "6/2*8/3",
                        "6/3/2*8",
                        "6/3*8/2",
                        "6*8/2/3",
                        "6*8/3/2",
                        "8/2/3*6",
                        "8/2*6/3",
                        "8/3/2*6",
                        "8/3*6/2",
                        "8*6/2/3",
                        "8*6/3/2"
                    ]
                },
                "(28, 36)": {
                    "('-',)": [
                        "36-28"
                    ]
                }
            }
        },
        {
            "date": "2024-07-08",
            "target": 27,
            "numbers": [
                2,
                5,
                7,
                9
            ],
            "solutions": 4,
            "hint": "29 or 72 or 25 or 79",
            "categorizedSolutions": {
                "(7, 9, 25)": {
                    "('+', '-')": [
                        "25-7+9",
                        "25+9-7",
                        "9+25-7",
                        "9-7+25"
                    ]
                },
                "(5, 7, 29)": {
                    "('+', '-')": [
                        "29+5-7",
                        "29-7+5",
                        "5+29-7",
                        "5-7+29"
                    ]
                },
                "(5, 9, 72)": {
                    "('*', '-')": [
                        "72-5*9",
                        "72-9*5"
                    ]
                },
                "(52, 79)": {
                    "('-',)": [
                        "79-52"
                    ]
                }
            }
        },
        {
            "date": "2024-07-09",
            "target": 28,
            "numbers": [
                3,
                5,
                6,
                9
            ],
            "solutions": 4,
            "hint": "-5 or 69 or 39 or 93",
            "categorizedSolutions": {
                "(5, 6, 39)": {
                    "('-', '-')": [
                        "39-5-6",
                        "39-6-5"
                    ]
                },
                "(3, 5, 6, 9)": {
                    "('*', '+', '-')": [
                        "3*9-5+6",
                        "3*9+6-5",
                        "6+3*9-5",
                        "6-5+3*9",
                        "6-5+9*3",
                        "6+9*3-5",
                        "9*3-5+6",
                        "9*3+6-5"
                    ]
                },
                "(3, 5, 69)": {
                    "('+', '/')": [
                        "5+69/3",
                        "69/3+5"
                    ]
                },
                "(65, 93)": {
                    "('-',)": [
                        "93-65"
                    ]
                }
            }
        },
        {
            "date": "2024-07-10",
            "target": 24,
            "numbers": [
                2,
                3,
                7,
                8
            ],
            "solutions": 5,
            "hint": "78 or 38 or 28 or 23 or 32",
            "categorizedSolutions": {
                "(7, 8, 23)": {
                    "('+', '-')": [
                        "23-7+8",
                        "23+8-7",
                        "8+23-7",
                        "8-7+23"
                    ]
                },
                "(3, 7, 28)": {
                    "('+', '-')": [
                        "28+3-7",
                        "28-7+3",
                        "3+28-7",
                        "3-7+28"
                    ]
                },
                "(2, 7, 38)": {
                    "('*', '-')": [
                        "38-2*7",
                        "38-7*2"
                    ]
                },
                "(2, 3, 78)": {
                    "('-', '/')": [
                        "78/3-2"
                    ]
                },
                "(7, 8, 32)": {
                    "('*', '-')": [
                        "7*8-32",
                        "8*7-32"
                    ]
                }
            }
        },
        {
            "date": "2024-07-11",
            "target": 2,
            "numbers": [
                3,
                4,
                6,
                8
            ],
            "solutions": 5,
            "hint": "*3 or -4 or /6 or 68 or 86",
            "categorizedSolutions": {
                "(3, 4, 6, 8)": {
                    "('*', '+', '-')": [
                        "6-3*4+8",
                        "6-4*3+8",
                        "6+8-3*4",
                        "6+8-4*3",
                        "8-3*4+6",
                        "8-4*3+6",
                        "8+6-3*4",
                        "8+6-4*3"
                    ],
                    "('-', '/', '/')": [
                        "8/3-4/6"
                    ],
                    "('-', '-', '/')": [
                        "8-4-6/3",
                        "8-6/3-4"
                    ]
                },
                "(34, 68)": {
                    "('/',)": [
                        "68/34"
                    ]
                },
                "(43, 86)": {
                    "('/',)": [
                        "86/43"
                    ]
                }
            }
        },
        {
            "date": "2024-07-12",
            "target": 3,
            "numbers": [
                2,
                7,
                8,
                9
            ],
            "solutions": 4,
            "hint": "*2 or -8 or 87 or 82",
            "categorizedSolutions": {
                "(2, 7, 8, 9)": {
                    "('*', '-', '-')": [
                        "2*9-7-8",
                        "2*9-8-7",
                        "9*2-7-8",
                        "9*2-8-7"
                    ],
                    "('*', '+', '-')": [
                        "8-2*7+9",
                        "8-7*2+9",
                        "8+9-2*7",
                        "8+9-7*2",
                        "9-2*7+8",
                        "9-7*2+8",
                        "9+8-2*7",
                        "9+8-7*2"
                    ]
                },
                "(79, 82)": {
                    "('-',)": [
                        "82-79"
                    ]
                },
                "(29, 87)": {
                    "('/',)": [
                        "87/29"
                    ]
                }
            }
        },
        {
            "date": "2024-07-13",
            "target": 27,
            "numbers": [
                3,
                4,
                6,
                9
            ],
            "solutions": 6,
            "hint": "*3 or /3 or -6 or 69 or 96 or 63",
            "categorizedSolutions": {
                "(3, 4, 6, 9)": {
                    "('*', '+', '+')": [
                        "3*4+6+9",
                        "3*4+9+6",
                        "4*3+6+9",
                        "4*3+9+6",
                        "6+3*4+9",
                        "6+4*3+9",
                        "6+9+3*4",
                        "6+9+4*3",
                        "9+3*4+6",
                        "9+4*3+6",
                        "9+6+3*4",
                        "9+6+4*3"
                    ],
                    "('*', '+', '/')": [
                        "4*6+9/3",
                        "6*4+9/3",
                        "9/3+4*6",
                        "9/3+6*4"
                    ],
                    "('*', '-', '-')": [
                        "4*9-3-6",
                        "4*9-6-3",
                        "9*4-3-6",
                        "9*4-6-3"
                    ]
                },
                "(3, 4, 96)": {
                    "('+', '/')": [
                        "3+96/4",
                        "96/4+3"
                    ]
                },
                "(3, 4, 69)": {
                    "('+', '/')": [
                        "4+69/3",
                        "69/3+4"
                    ]
                },
                "(4, 9, 63)": {
                    "('*', '-')": [
                        "63-4*9",
                        "63-9*4"
                    ]
                }
            }
        },
        {
            "date": "2024-07-14",
            "target": 4,
            "numbers": [
                2,
                4,
                5,
                7
            ],
            "solutions": 4,
            "hint": "+5 or +5 or -2 or /2",
            "categorizedSolutions": {
                "(2, 4, 5, 7)": {
                    "('+', '+', '-')": [
                        "2+4+5-7",
                        "2+4-7+5",
                        "2+5+4-7",
                        "2+5-7+4",
                        "2-7+4+5",
                        "2-7+5+4",
                        "4+2+5-7",
                        "4+2-7+5",
                        "4+5+2-7",
                        "4+5-7+2",
                        "4-7+2+5",
                        "4-7+5+2",
                        "5+2+4-7",
                        "5+2-7+4",
                        "5+4+2-7",
                        "5+4-7+2",
                        "5-7+2+4",
                        "5-7+4+2"
                    ],
                    "('+', '-', '-')": [
                        "4-2-5+7",
                        "4-2+7-5",
                        "4-5-2+7",
                        "4-5+7-2",
                        "4+7-2-5",
                        "4+7-5-2",
                        "7-2+4-5",
                        "7-2-5+4",
                        "7+4-2-5",
                        "7+4-5-2",
                        "7-5-2+4",
                        "7-5+4-2"
                    ],
                    "('+', '-', '/')": [
                        "4/2-5+7",
                        "4/2+7-5",
                        "7+4/2-5",
                        "7-5+4/2"
                    ],
                    "('*', '+', '-')": [
                        "5-2*4+7",
                        "5-4*2+7",
                        "5+7-2*4",
                        "5+7-4*2",
                        "7-2*4+5",
                        "7-4*2+5",
                        "7+5-2*4",
                        "7+5-4*2"
                    ]
                }
            }
        },
        {
            "date": "2024-07-15",
            "target": 29,
            "numbers": [
                3,
                4,
                8,
                9
            ],
            "solutions": 5,
            "hint": "+9 or -4 or *3 or /3 or 43",
            "categorizedSolutions": {
                "(3, 4, 8, 9)": {
                    "('*', '+', '+')": [
                        "3*4+8+9",
                        "3*4+9+8",
                        "4*3+8+9",
                        "4*3+9+8",
                        "8+3*4+9",
                        "8+4*3+9",
                        "8+9+3*4",
                        "8+9+4*3",
                        "9+3*4+8",
                        "9+4*3+8",
                        "9+8+3*4",
                        "9+8+4*3"
                    ],
                    "('*', '+', '-')": [
                        "3*8-4+9",
                        "3*8+9-4",
                        "8*3-4+9",
                        "8*3+9-4",
                        "9+3*8-4",
                        "9-4+3*8",
                        "9-4+8*3",
                        "9+8*3-4"
                    ],
                    "('*', '+', '/')": [
                        "3*9+8/4",
                        "8/4+3*9",
                        "8/4+9*3",
                        "9*3+8/4"
                    ],
                    "('*', '-', '/')": [
                        "4*8-9/3",
                        "8*4-9/3"
                    ]
                },
                "(8, 9, 43)": {
                    "('*', '-')": [
                        "8*9-43",
                        "9*8-43"
                    ]
                }
            }
        },
        {
            "date": "2024-07-16",
            "target": 18,
            "numbers": [
                2,
                3,
                6,
                7
            ],
            "solutions": 5,
            "hint": "-3 or +2 or 63 or 27 or 72",
            "categorizedSolutions": {
                "(2, 3, 6, 7)": {
                    "('+', '+', '+')": [
                        "2+3+6+7",
                        "2+3+7+6",
                        "2+6+3+7",
                        "2+6+7+3",
                        "2+7+3+6",
                        "2+7+6+3",
                        "3+2+6+7",
                        "3+2+7+6",
                        "3+6+2+7",
                        "3+6+7+2",
                        "3+7+2+6",
                        "3+7+6+2",
                        "6+2+3+7",
                        "6+2+7+3",
                        "6+3+2+7",
                        "6+3+7+2",
                        "6+7+2+3",
                        "6+7+3+2",
                        "7+2+3+6",
                        "7+2+6+3",
                        "7+3+2+6",
                        "7+3+6+2",
                        "7+6+2+3",
                        "7+6+3+2"
                    ],
                    "('*', '-', '/')": [
                        "3*7-6/2",
                        "6/2*7-3",
                        "6*7/2-3",
                        "7/2*6-3",
                        "7*3-6/2",
                        "7*6/2-3"
                    ]
                },
                "(2, 7, 63)": {
                    "('*', '/')": [
                        "2*63/7",
                        "2/7*63",
                        "63*2/7",
                        "63/7*2"
                    ]
                },
                "(3, 6, 27)": {
                    "('-', '-')": [
                        "27-3-6",
                        "27-6-3"
                    ]
                },
                "(3, 6, 72)": {
                    "('-', '/')": [
                        "72/3-6"
                    ]
                }
            }
        },
        {
            "date": "2024-07-17",
            "target": 29,
            "numbers": [
                3,
                4,
                5,
                6
            ],
            "solutions": 4,
            "hint": "+6 or -4 or 53 or 64",
            "categorizedSolutions": {
                "(3, 4, 5, 6)": {
                    "('*', '+', '+')": [
                        "3+4*5+6",
                        "3+5*4+6",
                        "3+6+4*5",
                        "3+6+5*4",
                        "4*5+3+6",
                        "4*5+6+3",
                        "5*4+3+6",
                        "5*4+6+3",
                        "6+3+4*5",
                        "6+3+5*4",
                        "6+4*5+3",
                        "6+5*4+3"
                    ],
                    "('*', '+', '-')": [
                        "3-4+5*6",
                        "3-4+6*5",
                        "3+5*6-4",
                        "3+6*5-4",
                        "5*6+3-4",
                        "5*6-4+3",
                        "6*5+3-4",
                        "6*5-4+3"
                    ]
                },
                "(4, 6, 53)": {
                    "('*', '-')": [
                        "53-4*6",
                        "53-6*4"
                    ]
                },
                "(35, 64)": {
                    "('-',)": [
                        "64-35"
                    ]
                }
            }
        },
        {
            "date": "2024-07-18",
            "target": 29,
            "numbers": [
                3,
                4,
                5,
                6
            ],
            "solutions": 4,
            "hint": "+6 or -4 or 53 or 64",
            "categorizedSolutions": {
                "(3, 4, 5, 6)": {
                    "('*', '+', '+')": [
                        "3+4*5+6",
                        "3+5*4+6",
                        "3+6+4*5",
                        "3+6+5*4",
                        "4*5+3+6",
                        "4*5+6+3",
                        "5*4+3+6",
                        "5*4+6+3",
                        "6+3+4*5",
                        "6+3+5*4",
                        "6+4*5+3",
                        "6+5*4+3"
                    ],
                    "('*', '+', '-')": [
                        "3-4+5*6",
                        "3-4+6*5",
                        "3+5*6-4",
                        "3+6*5-4",
                        "5*6+3-4",
                        "5*6-4+3",
                        "6*5+3-4",
                        "6*5-4+3"
                    ]
                },
                "(4, 6, 53)": {
                    "('*', '-')": [
                        "53-4*6",
                        "53-6*4"
                    ]
                },
                "(35, 64)": {
                    "('-',)": [
                        "64-35"
                    ]
                }
            }
        },
        {
            "date": "2024-07-19",
            "target": 21,
            "numbers": [
                2,
                3,
                7,
                9
            ],
            "solutions": 4,
            "hint": "+7 or 27 or 23 or 93",
            "categorizedSolutions": {
                "(7, 9, 23)": {
                    "('+', '-')": [
                        "23+7-9",
                        "23-9+7",
                        "7+23-9",
                        "7-9+23"
                    ]
                },
                "(2, 3, 7, 9)": {
                    "('+', '+', '+')": [
                        "2+3+7+9",
                        "2+3+9+7",
                        "2+7+3+9",
                        "2+7+9+3",
                        "2+9+3+7",
                        "2+9+7+3",
                        "3+2+7+9",
                        "3+2+9+7",
                        "3+7+2+9",
                        "3+7+9+2",
                        "3+9+2+7",
                        "3+9+7+2",
                        "7+2+3+9",
                        "7+2+9+3",
                        "7+3+2+9",
                        "7+3+9+2",
                        "7+9+2+3",
                        "7+9+3+2",
                        "9+2+3+7",
                        "9+2+7+3",
                        "9+3+2+7",
                        "9+3+7+2",
                        "9+7+2+3",
                        "9+7+3+2"
                    ]
                },
                "(3, 9, 27)": {
                    "('+', '-')": [
                        "27+3-9",
                        "27-9+3",
                        "3+27-9",
                        "3-9+27"
                    ]
                },
                "(72, 93)": {
                    "('-',)": [
                        "93-72"
                    ]
                }
            }
        },
        {
            "date": "2024-07-20",
            "target": 23,
            "numbers": [
                2,
                3,
                8,
                9
            ],
            "solutions": 4,
            "hint": "*2 or -3 or /2 or 39",
            "categorizedSolutions": {
                "(2, 3, 8, 9)": {
                    "('*', '+', '+')": [
                        "2*3+8+9",
                        "2*3+9+8",
                        "3*2+8+9",
                        "3*2+9+8",
                        "8+2*3+9",
                        "8+3*2+9",
                        "8+9+2*3",
                        "8+9+3*2",
                        "9+2*3+8",
                        "9+3*2+8",
                        "9+8+2*3",
                        "9+8+3*2"
                    ],
                    "('*', '+', '-')": [
                        "2*9-3+8",
                        "2*9+8-3",
                        "8+2*9-3",
                        "8-3+2*9",
                        "8-3+9*2",
                        "8+9*2-3",
                        "9*2-3+8",
                        "9*2+8-3"
                    ],
                    "('*', '-', '/')": [
                        "3*9-8/2",
                        "9*3-8/2"
                    ]
                },
                "(2, 8, 39)": {
                    "('*', '-')": [
                        "39-2*8",
                        "39-8*2"
                    ]
                }
            }
        },
        {
            "date": "2024-07-21",
            "target": 11,
            "numbers": [
                5,
                6,
                8,
                9
            ],
            "solutions": 3,
            "hint": "59 or 69 or 96",
            "categorizedSolutions": {
                "(6, 8, 59)": {
                    "('*', '-')": [
                        "59-6*8",
                        "59-8*6"
                    ]
                },
                "(58, 69)": {
                    "('-',)": [
                        "69-58"
                    ]
                },
                "(85, 96)": {
                    "('-',)": [
                        "96-85"
                    ]
                }
            }
        },
        {
            "date": "2024-07-22",
            "target": 28,
            "numbers": [
                2,
                3,
                5,
                9
            ],
            "solutions": 3,
            "hint": "35 or 25 or 32",
            "categorizedSolutions": {
                "(2, 9, 35)": {
                    "('+', '-')": [
                        "2+35-9",
                        "2-9+35",
                        "35+2-9",
                        "35-9+2"
                    ]
                },
                "(3, 9, 25)": {
                    "('+', '/')": [
                        "25+9/3",
                        "9/3+25"
                    ]
                },
                "(5, 9, 32)": {
                    "('+', '-')": [
                        "32+5-9",
                        "32-9+5",
                        "5+32-9",
                        "5-9+32"
                    ]
                }
            }
        },
        {
            "date": "2024-07-23",
            "target": 11,
            "numbers": [
                3,
                4,
                5,
                6
            ],
            "solutions": 7,
            "hint": "+5 or -3 or +4 or 56 or 35 or 46 or 64",
            "categorizedSolutions": {
                "(3, 4, 5, 6)": {
                    "('*', '+', '-')": [
                        "3*4+5-6",
                        "3*4-6+5",
                        "4*3+5-6",
                        "4*3-6+5",
                        "5+3*4-6",
                        "5+4*3-6",
                        "5-6+3*4",
                        "5-6+4*3"
                    ],
                    "('*', '-', '-')": [
                        "4*5-3-6",
                        "4*5-6-3",
                        "5*4-3-6",
                        "5*4-6-3"
                    ],
                    "('+', '+', '/')": [
                        "4+5+6/3",
                        "4+6/3+5",
                        "5+4+6/3",
                        "5+6/3+4",
                        "6/3+4+5",
                        "6/3+5+4"
                    ]
                },
                "(4, 6, 35)": {
                    "('*', '-')": [
                        "35-4*6",
                        "35-6*4"
                    ]
                },
                "(35, 46)": {
                    "('-',)": [
                        "46-35"
                    ]
                },
                "(3, 4, 56)": {
                    "('-', '/')": [
                        "56/4-3"
                    ]
                },
                "(53, 64)": {
                    "('-',)": [
                        "64-53"
                    ]
                }
            }
        },
        {
            "date": "2024-07-24",
            "target": 6,
            "numbers": [
                4,
                5,
                6,
                9
            ],
            "solutions": 3,
            "hint": "*5 or +4 or +6",
            "categorizedSolutions": {
                "(4, 5, 6, 9)": {
                    "('+', '+', '-')": [
                        "4+5+6-9",
                        "4+5-9+6",
                        "4+6+5-9",
                        "4+6-9+5",
                        "4-9+5+6",
                        "4-9+6+5",
                        "5+4+6-9",
                        "5+4-9+6",
                        "5+6+4-9",
                        "5+6-9+4",
                        "5-9+4+6",
                        "5-9+6+4",
                        "6+4+5-9",
                        "6+4-9+5",
                        "6+5+4-9",
                        "6+5-9+4",
                        "6-9+4+5",
                        "6-9+5+4"
                    ],
                    "('*', '*', '-')": [
                        "4*9-5*6",
                        "4*9-6*5",
                        "9*4-5*6",
                        "9*4-6*5"
                    ],
                    "('+', '-', '-')": [
                        "6-4-5+9",
                        "6-4+9-5",
                        "6-5-4+9",
                        "6-5+9-4",
                        "6+9-4-5",
                        "6+9-5-4",
                        "9-4-5+6",
                        "9-4+6-5",
                        "9-5-4+6",
                        "9-5+6-4",
                        "9+6-4-5",
                        "9+6-5-4"
                    ]
                }
            }
        },
        {
            "date": "2024-07-25",
            "target": 13,
            "numbers": [
                2,
                3,
                4,
                5
            ],
            "solutions": 8,
            "hint": "-4 or *4 or /2 or 45 or 25 or 24 or 32 or 45",
            "categorizedSolutions": {
                "(2, 3, 4, 5)": {
                    "('*', '+', '-')": [
                        "2+3*5-4",
                        "2-4+3*5",
                        "2-4+5*3",
                        "2+5*3-4",
                        "3*5+2-4",
                        "3*5-4+2",
                        "5*3+2-4",
                        "5*3-4+2"
                    ],
                    "('*', '+', '/')": [
                        "3+4/2*5",
                        "3+4*5/2",
                        "3+5/2*4",
                        "3+5*4/2",
                        "4/2*5+3",
                        "4*5/2+3",
                        "5/2*4+3",
                        "5*4/2+3"
                    ],
                    "('*', '-', '/')": [
                        "3*5-4/2",
                        "5*3-4/2"
                    ]
                },
                "(3, 5, 24)": {
                    "('+', '/')": [
                        "24/3+5",
                        "5+24/3"
                    ]
                },
                "(3, 4, 25)": {
                    "('*', '-')": [
                        "25-3*4",
                        "25-4*3"
                    ]
                },
                "(4, 5, 32)": {
                    "('+', '/')": [
                        "32/4+5",
                        "5+32/4"
                    ]
                },
                "(32, 45)": {
                    "('-',)": [
                        "45-32"
                    ]
                },
                "(2, 3, 45)": {
                    "('-', '/')": [
                        "45/3-2"
                    ]
                }
            }
        }
    ]
}